lantana/404.html
lantana/__init__.py
lantana/__main__.py
lantana/after_header.html
lantana/after_nav_tool.html
lantana/base.html
lantana/before_header.html
lantana/breadcrumb.html
lantana/favicon.png
lantana/favicon.svg
lantana/main.html
lantana/mkdocs_theme.yml
lantana/nav.html
lantana/sitemap.html
lantana/statics.html
lantana/toc.html
lantana/css/bootstrap-dark.min.css
lantana/css/bootstrap-icons-woff.css
lantana/css/bootstrap-icons-woff2.css
lantana/css/bootstrap-icons.min.css
lantana/css/bootstrap-icons.woff.css
lantana/css/bootstrap-icons.woff2.css
lantana/css/bootstrap-lite.min.css
lantana/css/bootstrap.min.css
lantana/css/default.min.css
lantana/css/theme.css
lantana/css/vs.min.css
lantana/css/fonts/bootstrap-icons.woff.css
lantana/css/fonts/bootstrap-icons.woff2.css
lantana/extensions/__init__.py
lantana/extensions/accordion.py
lantana/extensions/alerts.py
lantana/extensions/alerts2.py
lantana/extensions/cards.py
lantana/extensions/codeblock_copybtn.py
lantana/extensions/lantana.py
lantana/extensions/link_opennewtab.py
lantana/extensions/mdx_accordion.py
lantana/extensions/mdx_cards.py
lantana/extensions/mdx_embedly.py
lantana/extensions/mdx_lantana.py
lantana/extensions/mdx_mermaid_precompile.py
lantana/extensions/mdx_wsid.py
lantana/extensions/mermaid_precompile.py
lantana/extensions/mtables.py
lantana/extensions/selector.py
lantana/js/bootstrap.bundle.min.js
lantana/js/highlight.min.js
lantana/js/jquery-3.6.1.slim.min.js
lantana/js/theme.js
lantana-2.10.0.3.dist-info/LICENCE.md
lantana-2.10.0.3.dist-info/METADATA
lantana-2.10.0.3.dist-info/WHEEL
lantana-2.10.0.3.dist-info/entry_points.txt
lantana-2.10.0.3.dist-info/top_level.txt
lantana-2.10.0.3.dist-info/RECORD
