Metadata-Version: 2.1
Name: lantana
Version: 2.10.0.3
Summary: Bootstrap theme for MkDocs
Home-page: https://lantana.wsoft.ws/
Author: WSOFT
Author-email: info@wsoft.ws
License: MIT
Requires-Python: >=3.5
License-File: LICENCE.md
Requires-Dist: markdown (<3.4)
Requires-Dist: mkdocs (>=1.1)
Requires-Dist: pymdown-extensions
Requires-Dist: mkdocs-material
Requires-Dist: mkdocs-awesome-pages-plugin (>=2.3)
Requires-Dist: mkdocs-macros-plugin (>=0.6.3)
Requires-Dist: mkdocs-git-authors-plugin (>=0.6.2)
Requires-Dist: mkdocs-mermaid2-plugin (>=0.5.0)
Requires-Dist: mkdocs-git-revision-date-plugin (>=0.3.1)
Requires-Dist: natsort (>=8.3.1)
Requires-Dist: beautifulsoup4 (>=4.12.3)
Requires-Dist: html5lib (>=1.1)
